{"eCodCurso":"0000004","eAccion":"1","eCodEntidad":"1","fhFechaCurso":"2019-08-28 12:00:00","tTitulo":"Curso de Prueba de COPARMEX","tObjetivo":"Lorem ipsum dolor sit amet, consectetur adipiscing elit. Sed massa eros, accumsan non enim quis, feugiat finibus libero. Nulla ac justo velit. Donec commodo diam eget dui volutpat lobortis. Nam sed sapien dui. Quisque facilisis elit metus, quis dignissim quam commodo vitae. Mauris hendrerit sed urna sit amet mattis. Sed eget leo eget elit dignissim faucibus id sed odio. Donec at ante in sem malesuada scelerisque non et felis. Donec condimentum eget turpis id aliquet. Suspendisse sed diam rhoncus, placerat lacus a, porta eros. Nunc eros urna, pulvinar eget ornare sed, vulputate eu arcu.\r\n\r\nAenean ut erat in augue tempor interdum ut a dui. In ullamcorper posuere nisi, et aliquam mi feugiat eu. Quisque auctor, eros nec congue convallis, nisi velit luctus odio, eu eleifend leo augue non tellus. In nulla augue, vestibulum vel dignissim eget, maximus sit amet ipsum. Suspendisse quis mollis purus. Aliquam rhoncus finibus turpis vitae lobortis. Orci varius natoque penatibus et magnis dis parturient montes, nascetur ridiculus mus. Phasellus lobortis feugiat quam, non convallis tellus euismod quis. Phasellus congue ipsum in gravida tincidunt.","tDescripcion":"Lorem ipsum dolor sit amet, consectetur adipiscing elit. Sed massa eros, accumsan non enim quis, feugiat finibus libero. Nulla ac justo velit. Donec commodo diam eget dui volutpat lobortis. Nam sed sapien dui. Quisque facilisis elit metus, quis dignissim quam commodo vitae. Mauris hendrerit sed urna sit amet mattis. Sed eget leo eget elit dignissim faucibus id sed odio. Donec at ante in sem malesuada scelerisque non et felis. Donec condimentum eget turpis id aliquet. Suspendisse sed diam rhoncus, placerat lacus a, porta eros. Nunc eros urna, pulvinar eget ornare sed, vulputate eu arcu.\r\n\r\nAenean ut erat in augue tempor interdum ut a dui. In ullamcorper posuere nisi, et aliquam mi feugiat eu. Quisque auctor, eros nec congue convallis, nisi velit luctus odio, eu eleifend leo augue non tellus. In nulla augue, vestibulum vel dignissim eget, maximus sit amet ipsum. Suspendisse quis mollis purus. Aliquam rhoncus finibus turpis vitae lobortis. Orci varius natoque penatibus et magnis dis parturient montes, nascetur ridiculus mus. Phasellus lobortis feugiat quam, non convallis tellus euismod quis. Phasellus congue ipsum in gravida tincidunt.","eHoras":"10","tUbicacion":"Viaducto R\u00edo Becerra 168, San Pedro de los Pinos, 03800 Ciudad de M\u00e9xico, CDMX","modalidad":{"0":{"eLugares":"","dPrecio":""},"1":{"eCodModalidad":"1","eLugares":"5","dPrecio":"5"}},"modulos":{"1":{"eCodRegistro":"1","eModulo":"1","tNombre":"Modulo 1","fhFechaModulo":"28-08-2019 12:00","eHoras":"5","tEmbed":"https:\/\/www.nasa.gov\/nasalive\/"},"2":{"eCodRegistro":"","eModulo":"2","tNombre":"","fhFechaModulo":"","eHoras":"","tEmbed":""}},"eFilas":"3","tImagen":"\ufffd{\ufffd\ufffd\ufffd9wm9w\ufffd\ufffd\ufffd:`","tFicheroFlyer":"inv\/5d45d205d6af4.jpg","bFicheroFlyer":"1","tImagen2":"\ufffd{\ufffd\ufffd\ufffd9wm9w\ufffd}\ufffd:`","tFicheroSlider":"inv\/5d45d205d8d91.jpg","bFicheroSlider":"1"}